Metadata-Version: 2.4
Name: airbender-py-anthropic
Version: 0.2.12
Summary: Anthropic provider for Airbender Python SDK
Author-email: "Rangle.io" <info@rangle.io>
License: Apache-2.0
Requires-Python: >=3.12
Requires-Dist: annotated-types==0.7.0
Requires-Dist: anthropic==0.54.0
Requires-Dist: anyio==4.9.0
Requires-Dist: certifi==2025.6.15
Requires-Dist: colorama==0.4.6; sys_platform == 'win32'
Requires-Dist: distro==1.9.0
Requires-Dist: h11==0.16.0
Requires-Dist: httpcore==1.0.9
Requires-Dist: httpx==0.28.1
Requires-Dist: idna==3.10
Requires-Dist: iniconfig==2.1.0
Requires-Dist: jiter==0.10.0
Requires-Dist: mypy-extensions==1.1.0
Requires-Dist: mypy==1.16.1
Requires-Dist: packaging==24.2
Requires-Dist: pathspec==0.12.1
Requires-Dist: pluggy==1.6.0
Requires-Dist: pydantic-core==2.33.2
Requires-Dist: pydantic==2.11.7
Requires-Dist: pygments==2.19.1
Requires-Dist: pytest-asyncio==1.0.0
Requires-Dist: pytest-httpx==0.35.0
Requires-Dist: pytest==8.4.0
Requires-Dist: python-dotenv==1.1.0
Requires-Dist: ruff==0.11.13
Requires-Dist: sniffio==1.3.1
Requires-Dist: typing-extensions==4.14.0
Requires-Dist: typing-inspection==0.4.1
Provides-Extra: dev
Requires-Dist: mypy; extra == 'dev'
Requires-Dist: pytest; extra == 'dev'
Requires-Dist: pytest-asyncio; extra == 'dev'
Requires-Dist: pytest-httpx; extra == 'dev'
Requires-Dist: ruff; extra == 'dev'
